py_whatsapp_cloudbot-0.1.3.1.dist-info/licenses/LICENSE
wa_cloud/__init__.py
wa_cloud/application.py
wa_cloud/bot.py
wa_cloud/constants.py
wa_cloud/error.py
wa_cloud/http_client.py
wa_cloud/models.py
wa_cloud/webhooks.py
wa_cloud/ext/__init__.py
wa_cloud/ext/basehandler.py
wa_cloud/ext/filters.py
wa_cloud/ext/messagehandler.py
py_whatsapp_cloudbot-0.1.3.1.dist-info/METADATA
py_whatsapp_cloudbot-0.1.3.1.dist-info/WHEEL
py_whatsapp_cloudbot-0.1.3.1.dist-info/top_level.txt
py_whatsapp_cloudbot-0.1.3.1.dist-info/RECORD
