Metadata-Version: 2.4
Name: py-whatsapp-cloudbot
Version: 0.1.3.1
Summary: An asynchronous Python library for the WhatsApp Cloud API.
Home-page: https://github.com/ardatricity/py-whatsapp-cloudbot
Author: Arda Koçak
Author-email: ardatricity@gmail.com
License: LGPL-3.0-or-later
Project-URL: Bug Tracker, https://github.com/ardatricity/py-whatsapp-cloudbot/issues
Project-URL: Repository, https://github.com/ardatricity/py-whatsapp-cloudbot
Classifier: Development Status :: 3 - Alpha
Classifier: Intended Audience :: Developers
Classifier: License :: OSI Approved :: GNU Lesser General Public License v3 or later (LGPLv3+)
Classifier: Operating System :: OS Independent
Classifier: Programming Language :: Python :: 3.8
Classifier: Programming Language :: Python :: 3.9
Classifier: Programming Language :: Python :: 3.10
Classifier: Programming Language :: Python :: 3.11
Classifier: Programming Language :: Python :: 3.12
Classifier: Topic :: Communications :: Chat
Classifier: Topic :: Software Development :: Libraries :: Python Modules
Classifier: Typing :: Typed
Requires-Python: >=3.8
License-File: LICENSE
Requires-Dist: httpx>=0.24.0
Requires-Dist: pydantic>=2.0.0
Provides-Extra: fastapi
Requires-Dist: fastapi>=0.100.0; extra == "fastapi"
Requires-Dist: uvicorn[standard]>=0.20.0; extra == "fastapi"
Provides-Extra: dev
Dynamic: author
Dynamic: author-email
Dynamic: classifier
Dynamic: description
Dynamic: description-content-type
Dynamic: home-page
Dynamic: license
Dynamic: license-file
Dynamic: project-url
Dynamic: provides-extra
Dynamic: requires-dist
Dynamic: requires-python
Dynamic: summary
